Topsis_Sahil/102183056.py
Topsis_Sahil/__init__.py
TOPSIS_Sahil_Rohilla_102183056-1.0.4.dist-info/LICENSE.txt
TOPSIS_Sahil_Rohilla_102183056-1.0.4.dist-info/METADATA
TOPSIS_Sahil_Rohilla_102183056-1.0.4.dist-info/WHEEL
TOPSIS_Sahil_Rohilla_102183056-1.0.4.dist-info/top_level.txt
TOPSIS_Sahil_Rohilla_102183056-1.0.4.dist-info/RECORD
